main.py
franktestcat2-0.1.0.dist-info/METADATA
franktestcat2-0.1.0.dist-info/WHEEL
franktestcat2-0.1.0.dist-info/entry_points.txt
franktestcat2-0.1.0.dist-info/top_level.txt
franktestcat2-0.1.0.dist-info/RECORD
